bayesianpia2/__init__.py
bayesianpia2-0.0.5.dist-info/METADATA
bayesianpia2-0.0.5.dist-info/WHEEL
bayesianpia2-0.0.5.dist-info/RECORD
